BramSchreuderMLTools/Tools.py
BramSchreuderMLTools/__init__.py
BramSchreuderMLTools-0.0.2.dist-info/LICENSE.txt
BramSchreuderMLTools-0.0.2.dist-info/METADATA
BramSchreuderMLTools-0.0.2.dist-info/WHEEL
BramSchreuderMLTools-0.0.2.dist-info/top_level.txt
BramSchreuderMLTools-0.0.2.dist-info/RECORD
